iimcsim/MC.py
iimcsim/MODELS.py
iimcsim/MonteCarlo.py
iimcsim/__init__.py
iimcsim/data_gen.py
iimcsim/data_gen_run.py
iimcsim/eda.py
iimcsim/shape_ext.py
iimcsim/tools.py
iimcsim/unet_models.py
iimcsim-0.1.9.dist-info/LICENSE
iimcsim-0.1.9.dist-info/METADATA
iimcsim-0.1.9.dist-info/WHEEL
iimcsim-0.1.9.dist-info/top_level.txt
iimcsim-0.1.9.dist-info/RECORD
