Metadata-Version: 2.1
Name: iimcsim
Version: 0.1.9
Summary: A package for Monte-Carlo simulation for Intensity Interferometry
Home-page: https://github.com/jigar2099/photon_position_reconstruction/tree/main
Author: Jigar Bhanderi
Author-email: jigarbhanderi@gmail.com
Project-URL: Bug Tracker, https://github.com/jigar2099/photon_position_reconstruction/issues
Classifier: Programming Language :: Python :: 3
Classifier: License :: OSI Approved :: MIT License
Classifier: Operating System :: OS Independent
Requires-Python: >=3.6
License-File: LICENSE
